aospdtgen/__init__.py
aospdtgen/__main__.py
aospdtgen/device_tree.py
aospdtgen/main.py
aospdtgen/proprietary_files/elf.py
aospdtgen/proprietary_files/get_vndk_libs.py
aospdtgen/proprietary_files/ignore.py
aospdtgen/proprietary_files/proprietary_files_list.py
aospdtgen/proprietary_files/section.py
aospdtgen/proprietary_files/sections/acdb.py
aospdtgen/proprietary_files/sections/adsp.py
aospdtgen/proprietary_files/sections/alarm.py
aospdtgen/proprietary_files/sections/ant.py
aospdtgen/proprietary_files/sections/atrace.py
aospdtgen/proprietary_files/sections/audio.py
aospdtgen/proprietary_files/sections/authsecret.py
aospdtgen/proprietary_files/sections/automotive.py
aospdtgen/proprietary_files/sections/bluetooth.py
aospdtgen/proprietary_files/sections/boot.py
aospdtgen/proprietary_files/sections/broadcastradio.py
aospdtgen/proprietary_files/sections/camera.py
aospdtgen/proprietary_files/sections/cas.py
aospdtgen/proprietary_files/sections/cdsp.py
aospdtgen/proprietary_files/sections/cit.py
aospdtgen/proprietary_files/sections/cne.py
aospdtgen/proprietary_files/sections/configstore.py
aospdtgen/proprietary_files/sections/confirmationui.py
aospdtgen/proprietary_files/sections/contexthub.py
aospdtgen/proprietary_files/sections/cvp.py
aospdtgen/proprietary_files/sections/display.py
aospdtgen/proprietary_files/sections/dpm.py
aospdtgen/proprietary_files/sections/drm.py
aospdtgen/proprietary_files/sections/dsp.py
aospdtgen/proprietary_files/sections/dumpstate.py
aospdtgen/proprietary_files/sections/face.py
aospdtgen/proprietary_files/sections/fastboot.py
aospdtgen/proprietary_files/sections/fingerprint.py
aospdtgen/proprietary_files/sections/fm.py
aospdtgen/proprietary_files/sections/gatekeeper.py
aospdtgen/proprietary_files/sections/gnss.py
aospdtgen/proprietary_files/sections/health.py
aospdtgen/proprietary_files/sections/identity.py
aospdtgen/proprietary_files/sections/input.py
aospdtgen/proprietary_files/sections/ipa.py
aospdtgen/proprietary_files/sections/ir.py
aospdtgen-1.1.1.dist-info/METADATA
aospdtgen-1.1.1.dist-info/WHEEL
aospdtgen-1.1.1.dist-info/entry_points.txt
aospdtgen-1.1.1.dist-info/RECORD
