Metadata-Version: 2.1
Name: aospdtgen
Version: 1.1.1
Summary: Create an Android device tree from a device dump
Home-page: https://github.com/sebaubuntu-python/aospdtgen
License: Apache-2.0
Author: Sebastiano Barezzi
Author-email: seba@sebaubuntu.dev
Requires-Python: >=3.8,<4.0
Classifier: License :: OSI Approved :: Apache Software License
Classifier: Programming Language :: Python :: 3
Classifier: Programming Language :: Python :: 3.8
Classifier: Programming Language :: Python :: 3.9
Classifier: Programming Language :: Python :: 3.10
Classifier: Programming Language :: Python :: 3.11
Classifier: Programming Language :: Python :: 3.12
Requires-Dist: GitPython (>=3.1.31,<4.0.0)
Requires-Dist: Jinja2 (>=3.1.2,<4.0.0)
Requires-Dist: sebaubuntu-libs (>=1.4.2,<2.0.0)
Project-URL: Repository, https://github.com/sebaubuntu-python/aospdtgen
